interview/__init__.py
interview/interview.py
interview_buddy-0.4.dist-info/METADATA
interview_buddy-0.4.dist-info/WHEEL
interview_buddy-0.4.dist-info/top_level.txt
interview_buddy-0.4.dist-info/RECORD
