Metadata-Version: 2.1
Name: interview-buddy
Version: 0.4
Summary: This package is made for beginners who are appearing for interview preparation and to crack coding interviews
Author: R Jeyaraman
Author-email: jeyaramanjr7@gmail.com
Requires-Dist: transformers
Requires-Dist: ctransformers
